README.md
setup.py
crun/__init__.py
crun/builtin.py
crun/fanciness.py
crun/runner.py
crun.egg-info/PKG-INFO
crun.egg-info/SOURCES.txt
crun.egg-info/dependency_links.txt
crun.egg-info/entry_points.txt
crun.egg-info/requires.txt
crun.egg-info/top_level.txt