Metadata-Version: 1.1
Name: crun
Version: 2.6.0
Summary: Run pipelines according to configuration files
Home-page: https://github.com/L3viathan/crun
Author: L3viathan
Author-email: git@l3vi.de
License: UNKNOWN
Platform: UNKNOWN
Classifier: Programming Language :: Python :: 3
Classifier: Operating System :: OS Independent
Classifier: Environment :: Console
Classifier: Intended Audience :: Developers
